prgai/__init__.py
prgai/prg.py
prgai-0.0.1.dist-info/METADATA
prgai-0.0.1.dist-info/WHEEL
prgai-0.0.1.dist-info/top_level.txt
prgai-0.0.1.dist-info/RECORD
